brx/__init__.py
brx-0.1.5.dist-info/METADATA
brx-0.1.5.dist-info/WHEEL
brx-0.1.5.dist-info/RECORD
