Metadata-Version: 2.1
Name: brx
Version: 0.1.5
Summary: Use the BRX API using Python.
Author: BRX
Requires-Python: >=3.10,<4.0
Classifier: Programming Language :: Python :: 3
Classifier: Programming Language :: Python :: 3.10
Classifier: Programming Language :: Python :: 3.11
Classifier: Programming Language :: Python :: 3.12
Requires-Dist: websocket-client (>=1.7.0,<2.0.0)
